percy-2.0.2.dist-info/RECORD
percy-2.0.2.dist-info/metadata.json
percy-2.0.2.dist-info/WHEEL
percy-2.0.2.dist-info/DESCRIPTION.rst
percy-2.0.2.dist-info/top_level.txt
percy-2.0.2.dist-info/METADATA
percy/user_agent.py
percy/runner.py
percy/config.py
percy/client.py
percy/resource.py
percy/__init__.py
percy/resource_loader.py
percy/connection.py
percy/utils.py
percy/environment.py
percy/errors.py
